suga/__init__.py
suga/buckets.py
suga/gen/__init__.py
suga/gen/pubsub/__init__.py
suga/gen/pubsub/v2/__init__.py
suga/gen/pubsub/v2/pubsub_pb2.py
suga/gen/pubsub/v2/pubsub_pb2_grpc.py
suga/gen/storage/__init__.py
suga/gen/storage/v2/__init__.py
suga/gen/storage/v2/storage_pb2.py
suga/gen/storage/v2/storage_pb2_grpc.py
suga_client-0.6.3.dist-info/METADATA
suga_client-0.6.3.dist-info/WHEEL
suga_client-0.6.3.dist-info/top_level.txt
suga_client-0.6.3.dist-info/RECORD
