Metadata-Version: 2.4
Name: suga-client
Version: 0.6.3
Summary: Suga Python Client
License-Expression: MPL-2.0
Requires-Python: >=3.10
Requires-Dist: grpcio
Requires-Dist: grpcio-tools
Requires-Dist: protobuf
